<annotation>
	<folder>images</folder>
	<filename>2024-07-16 21-16-18_000160.jpg</filename>
	<path>C:\Users\zhaoz\Desktop\Human-Body-Detector-and-Auto-Follower-main\dataset\ds1\images\2024-07-16 21-16-18_000160.jpg</path>
	<source>
		<database>Unknown</database>
	</source>
	<size>
		<width>1920</width>
		<height>1080</height>
		<depth>3</depth>
	</size>
	<segmented>0</segmented>
	<object>
		<name>human</name>
		<pose>Unspecified</pose>
		<truncated>0</truncated>
		<difficult>0</difficult>
		<bndbox>
			<xmin>977</xmin>
			<ymin>545</ymin>
			<xmax>1023</xmax>
			<ymax>668</ymax>
		</bndbox>
	</object>
	<object>
		<name>human</name>
		<pose>Unspecified</pose>
		<truncated>0</truncated>
		<difficult>0</difficult>
		<bndbox>
			<xmin>1102</xmin>
			<ymin>533</ymin>
			<xmax>1140</xmax>
			<ymax>634</ymax>
		</bndbox>
	</object>
</annotation>
